eks_auth/__init__.py
eks_auth/eks_auth.py
eks_auth/aws/__init__.py
eks_auth/aws/client.py
eks_auth/aws/eks.py
eks_auth/profile/__init__.py
eks_auth/profile/creator.py
eks_auth/profile/profile.py
eks_auth/profile/selector.py
eks_auth/tools/__init__.py
eks_auth/tools/inquire.py
eks_auth/tools/userAccept.py
eks_auth-0.1.1.dist-info/AUTHORS.rst
eks_auth-0.1.1.dist-info/LICENSE
eks_auth-0.1.1.dist-info/METADATA
eks_auth-0.1.1.dist-info/WHEEL
eks_auth-0.1.1.dist-info/top_level.txt
eks_auth-0.1.1.dist-info/RECORD
