Metadata-Version: 2.1
Name: eks-auth
Version: 0.1.1
Summary: Authentication tool, for IAM users to access EKS cluster.
Home-page: https://github.com/ElDiabloRojo/eks_auth
Author: Sam Holden
Author-email: holdens.uk@googlemail.com
License: MIT license
Keywords: eks_auth
Platform: UNKNOWN
Classifier: Development Status :: 2 - Pre-Alpha
Classifier: Intended Audience :: Developers
Classifier: License :: OSI Approved :: MIT License
Classifier: Natural Language :: English
Classifier: Programming Language :: Python :: 3
Classifier: Programming Language :: Python :: 3.6
Classifier: Programming Language :: Python :: 3.7
Classifier: Programming Language :: Python :: 3.8
Requires-Python: >=3.6
